intake_salesforce/__init__.py
intake_salesforce/_version.py
intake_salesforce/core.py
intake_salesforce/versioneer.py
intake_salesforce-0.0.10.dist-info/LICENSE
intake_salesforce-0.0.10.dist-info/METADATA
intake_salesforce-0.0.10.dist-info/WHEEL
intake_salesforce-0.0.10.dist-info/entry_points.txt
intake_salesforce-0.0.10.dist-info/top_level.txt
intake_salesforce-0.0.10.dist-info/RECORD
